Workbook

Sheet Dashboard
A1: FIN-W5-ENTERPRISE-05 | AUTOMATED FP&A EXECUTIVE DASHBOARD
P2: Month | Q2: Revenue | R2: Expenses | S2: EBITDA | T2: Net Profit | U2: Cash
A3: AUTOMATION CONTROLS | P3: =Monthly_PnL!A3 -> 45658 | Q3: =Monthly_PnL!B3 -> 2059800 | R3: =Monthly_PnL!E3 -> 1366200 | S3: =Monthly_PnL!F3 -> -27330 | T3: =Monthly_PnL!J3 -> -78825 | U3: =CashFlow!L3 -> 6337876
A4: Selected Month | B4: 45931 | D4: Change the Month or Scenario dropdown. KPIs, alerts, comparisons and charts are formula-linked and recalculate automatically. | P4: =Monthly_PnL!A4 -> 45689 | Q4: =Monthly_PnL!B4 -> 2160300 | R4: =Monthly_PnL!E4 -> 1424700 | S4: =Monthly_PnL!F4 -> -20505 | T4: =Monthly_PnL!J4 -> -74512.5 | U4: =CashFlow!L4 -> 7282950
A5: Scenario | B5: Upside | P5: =Monthly_PnL!A5 -> 45717 | Q5: =Monthly_PnL!B5 -> 2263000 | R5: =Monthly_PnL!E5 -> 1427600 | S5: =Monthly_PnL!F5 -> 43350 | T5: =Monthly_PnL!J5 -> -13225 | U5: =CashFlow!L5 -> 8103950
A6: As-of Date | B6: =B4 -> 45931 | P6: =Monthly_PnL!A6 -> 45748 | Q6: =Monthly_PnL!B6 -> 2344800 | R6: =Monthly_PnL!E6 -> 1487600 | S6: =Monthly_PnL!F6 -> 36520 | T6: =Monthly_PnL!J6 -> -22100 | U6: =CashFlow!L6 -> 8801829
P7: =Monthly_PnL!A7 -> 45778 | Q7: =Monthly_PnL!B7 -> 2428100 | R7: =Monthly_PnL!E7 -> 1446400 | S7: =Monthly_PnL!F7 -> 131865 | T7: =Monthly_PnL!J7 -> 53371.875 | U7: =CashFlow!L7 -> 9798552
A8: Revenue | D8: Operating Expenses | G8: EBITDA | J8: Net Profit | P8: =Monthly_PnL!A8 -> 45809 | Q8: =Monthly_PnL!B8 -> 2536500 | R8: =Monthly_PnL!E8 -> 1507200 | S8: =Monthly_PnL!F8 -> 141525 | T8: =Monthly_PnL!J8 -> 58584.375 | U8: =CashFlow!L8 -> 10747637
B9: =SUMIFS(Monthly_PnL!$B:$B,Monthly_PnL!$A:$A,$B$4) -> 2815700 | E9: =SUMIFS(Monthly_PnL!$E:$E,Monthly_PnL!$A:$A,$B$4) -> 1575600 | H9: =SUMIFS(Monthly_PnL!$F:$F,Monthly_PnL!$A:$A,$B$4) -> 254605 | K9: =SUMIFS(Monthly_PnL!$J:$J,Monthly_PnL!$A:$A,$B$4) -> 138159.38 | P9: =Monthly_PnL!A9 -> 45839 | Q9: =Monthly_PnL!B9 -> 2526700 | R9: =Monthly_PnL!E9 -> 1554200 | S9: =Monthly_PnL!F9 -> 88155 | T9: =Monthly_PnL!J9 -> 18740.625 | U9: =CashFlow!L9 -> 11994288
P10: =Monthly_PnL!A10 -> 45870 | Q10: =Monthly_PnL!B10 -> 2637700 | R10: =Monthly_PnL!E10 -> 1511300 | S10: =Monthly_PnL!F10 -> 203205 | T10: =Monthly_PnL!J10 -> 102946.88 | U10: =CashFlow!L10 -> 13090809
P11: =Monthly_PnL!A11 -> 45901 | Q11: =Monthly_PnL!B11 -> 2725900 | R11: =Monthly_PnL!E11 -> 1604100 | S11: =Monthly_PnL!F11 -> 167735 | T11: =Monthly_PnL!J11 -> 74690.625 | U11: =CashFlow!L11 -> 14058196
A12: Closing Cash | D12: AR Outstanding | G12: AP Outstanding | J12: Current Ratio | P12: =Monthly_PnL!A12 -> 45931 | Q12: =Monthly_PnL!B12 -> 2815700 | R12: =Monthly_PnL!E12 -> 1575600 | S12: =Monthly_PnL!F12 -> 254605 | T12: =Monthly_PnL!J12 -> 138159.38 | U12: =CashFlow!L12 -> 15322962
B13: =INDEX(CashFlow!$L:$L,MATCH($B$4,CashFlow!$A:$A,0)) -> 14058196 | E13: =SUM(AR_Aging!$G:$G) -> 7524800 | H13: =SUM(AP_Aging!$G:$G) -> 4110600 | K13: =INDEX(Working_Capital!$H:$H,MATCH($B$4,Working_Capital!$A:$A,0)) -> 5.2505707 | P13: =Monthly_PnL!A13 -> 45962 | Q13: =Monthly_PnL!B13 -> 2957800 | R13: =Monthly_PnL!E13 -> 1670400 | S13: =Monthly_PnL!F13 -> 252170 | T13: =Monthly_PnL!J13 -> 133668.75 | U13: =CashFlow!L13 -> 16720561
P14: =Monthly_PnL!A14 -> 45992 | Q14: =Monthly_PnL!B14 -> 3154500 | R14: =Monthly_PnL!E14 -> 1735800 | S14: =Monthly_PnL!F14 -> 314625 | T14: =Monthly_PnL!J14 -> 176821.88 | U14: =CashFlow!L14 -> 0
A17: SELECTED MONTH PERFORMANCE | F17: SCENARIO COMPARISON | K17: AUTOMATIC MANAGEMENT ALERTS
A18: Metric | B18: Selected Month | C18: YTD | D18: FY2025 | F18: Scenario | G18: Revenue | H18: EBITDA | I18: Net Profit | K18: Alert | L18: Status | M18: Recommended Action | P18: Category | Q18: Amount
A19: Revenue | B19: =SUMIFS(Monthly_PnL!$B:$B,Monthly_PnL!$A:$A,$B$4) -> 2815700 | C19: =SUMIFS(Monthly_PnL!$B:$B,Monthly_PnL!$A:$A,">="&DATE(YEAR($B$4),1,1),Monthly_PnL!$A:$A,"<="&$B$4) -> 24498500 | D19: =SUM(Monthly_PnL!$B$3:$B$14) -> 30610800 | F19: =Scenarios!A2 -> Base | G19: =Scenarios!D2 -> 3154500 | H19: =Scenarios!G2 -> 314625 | I19: =Scenarios!H2 -> 235968.75 | K19: Budget utilization | L19: =IF(MAX(Budget!$E$2:$E$7)>1,"HIGH",IF(MAX(Budget!$E$2:$E$7)>0.9,"WATCH","OK")) -> WATCH | M19: =IF(L19="HIGH","Review overspent departments",IF(L19="WATCH","Monitor departments nearing budget","No action")) -> Monitor departments nearing budget | P19: Employee Costs | Q19: =SUMIFS(Expenses!$E:$E,Expenses!$D:$D,P19) -> 9457400
A20: EBITDA | B20: =SUMIFS(Monthly_PnL!$F:$F,Monthly_PnL!$A:$A,$B$4) -> 254605 | C20: =SUMIFS(Monthly_PnL!$F:$F,Monthly_PnL!$A:$A,">="&DATE(YEAR($B$4),1,1),Monthly_PnL!$A:$A,"<="&$B$4) -> 1019125 | D20: =SUM(Monthly_PnL!$F$3:$F$14) -> 1585920 | F20: =Scenarios!A3 -> Upside | G20: =Scenarios!D3 -> 3469950 | H20: =Scenarios!G3 -> 571741.5 | I20: =Scenarios!H3 -> 428806.13 | K20: Liquidity | L20: =IF(INDEX(Working_Capital!$H:$H,MATCH($B$4,Working_Capital!$A:$A,0))<1,"HIGH",IF(INDEX(Working_Capital!$H:$H,MATCH($B$4,Working_Capital!$A:$A,0))<1.5,"WATCH","OK")) -> OK | M20: =IF(L20="HIGH","Protect cash and accelerate collections",IF(L20="WATCH","Monitor liquidity","No action")) -> No action | P20: Infrastructure | Q20: =SUMIFS(Expenses!$E:$E,Expenses!$D:$D,P20) -> 2167500
A21: Net Profit | B21: =SUMIFS(Monthly_PnL!$J:$J,Monthly_PnL!$A:$A,$B$4) -> 138159.38 | C21: =SUMIFS(Monthly_PnL!$J:$J,Monthly_PnL!$A:$A,">="&DATE(YEAR($B$4),1,1),Monthly_PnL!$A:$A,"<="&$B$4) -> 257831.25 | D21: =SUM(Monthly_PnL!$J$3:$J$14) -> 568321.88 | F21: =Scenarios!A4 -> Downside | G21: =Scenarios!D4 -> 2839050 | H21: =Scenarios!G4 -> -29281.5 | I21: =Scenarios!H4 -> -29281.5 | K21: AR aging | L21: =IF(COUNTIFS(AR_Aging!$I:$I,">90",AR_Aging!$G:$G,">0")>0,"HIGH",IF(COUNTIFS(AR_Aging!$I:$I,">60",AR_Aging!$G:$G,">0")>0,"WATCH","OK")) -> HIGH | M21: =IF(L21="HIGH","Escalate 90+ day receivables",IF(L21="WATCH","Follow up overdue customers","No action")) -> Escalate 90+ day receivables | P21: Marketing | Q21: =SUMIFS(Expenses!$E:$E,Expenses!$D:$D,P21) -> 1839100
K22: Profitability | L22: =IF(SUM(Monthly_PnL!$J$3:$J$14)<0,"HIGH",IF(AVERAGE(Monthly_PnL!$L$3:$L$14)<0.1,"WATCH","OK")) -> WATCH | M22: =IF(L22="HIGH","Review cost and revenue drivers",IF(L22="WATCH","Monitor net margin","No action")) -> Monitor net margin | P22: Travel | Q22: =SUMIFS(Expenses!$E:$E,Expenses!$D:$D,P22) -> 853900
P23: Software | Q23: =SUMIFS(Expenses!$E:$E,Expenses!$D:$D,P23) -> 1510500
P24: Professional Fees | Q24: =SUMIFS(Expenses!$E:$E,Expenses!$D:$D,P24) -> 0
P25: Office Expenses | Q25: =SUMIFS(Expenses!$E:$E,Expenses!$D:$D,P25) -> 0
P26: Other | Q26: =SUMIFS(Expenses!$E:$E,Expenses!$D:$D,P26) -> 0
P27: =Budget!A2 -> Engineering | Q27: =Budget!B2 -> 10809700 | R27: =Budget!C2 -> 10009000
P28: =Budget!A3 -> IT | Q28: =Budget!B3 -> 3135800 | R28: =Budget!C3 -> 2850700
P29: =Budget!A4 -> Sales & Marketing | Q29: =Budget!B4 -> 1931100 | R29: =Budget!C4 -> 1839100
P30: =Budget!A5 -> Operations | Q30: =Budget!B5 -> 913700 | R30: =Budget!C5 -> 853900
P31: =Budget!A6 -> HR | Q31: =Budget!B6 -> 1691800 | R31: =Budget!C6 -> 1510500
P32: =Budget!A7 -> Finance & Admin | Q32: =Budget!B7 -> 1322800 | R32: =Budget!C7 -> 1247900

Sheet Revenue
A1: Invoice_ID | B1: Date | C1: Business_Unit | D1: Region | E1: Customer | F1: Revenue | G1: Currency | H1: Year | I1: Month | J1: Quarter
A2: REV-2501-1001 | B2: 45658 | C2: Software Development | D2: North | E2: Alpha Industries | F2: 833300 | G2: INR | H2: =YEAR(B2) -> 2025 | I2: =TEXT(B2,"mmm") -> Jan | J2: ="Q"&ROUNDUP(MONTH(B2)/3,0) -> Q1
A3: REV-2501-1002 | B3: 45658 | C3: Website Development | D3: South | E3: Crest Healthcare | F3: 486400 | G3: INR | H3: =YEAR(B3) -> 2025 | I3: =TEXT(B3,"mmm") -> Jan | J3: ="Q"&ROUNDUP(MONTH(B3)/3,0) -> Q1
A4: REV-2501-1003 | B4: 45658 | C4: AMC & Maintenance | D4: West | E4: Evergreen Finance | F4: 406200 | G4: INR | H4: =YEAR(B4) -> 2025 | I4: =TEXT(B4,"mmm") -> Jan | J4: ="Q"&ROUNDUP(MONTH(B4)/3,0) -> Q1
A5: REV-2501-1004 | B5: 45658 | C5: IT Consulting | D5: East | E5: Alpha Industries | F5: 333900 | G5: INR | H5: =YEAR(B5) -> 2025 | I5: =TEXT(B5,"mmm") -> Jan | J5: ="Q"&ROUNDUP(MONTH(B5)/3,0) -> Q1
A6: REV-2502-1005 | B6: 45689 | C6: Software Development | D6: South | E6: Bright Retail | F6: 874000 | G6: INR | H6: =YEAR(B6) -> 2025 | I6: =TEXT(B6,"mmm") -> Feb | J6: ="Q"&ROUNDUP(MONTH(B6)/3,0) -> Q1
A7: REV-2502-1006 | B7: 45689 | C7: Website Development | D7: West | E7: Delta Logistics | F7: 510100 | G7: INR | H7: =YEAR(B7) -> 2025 | I7: =TEXT(B7,"mmm") -> Feb | J7: ="Q"&ROUNDUP(MONTH(B7)/3,0) -> Q1
A8: REV-2502-1007 | B8: 45689 | C8: AMC & Maintenance | D8: East | E8: FutureTech | F8: 426000 | G8: INR | H8: =YEAR(B8) -> 2025 | I8: =TEXT(B8,"mmm") -> Feb | J8: ="Q"&ROUNDUP(MONTH(B8)/3,0) -> Q1
A9: REV-2502-1008 | B9: 45689 | C9: IT Consulting | D9: North | E9: Bright Retail | F9: 350200 | G9: INR | H9: =YEAR(B9) -> 2025 | I9: =TEXT(B9,"mmm") -> Feb | J9: ="Q"&ROUNDUP(MONTH(B9)/3,0) -> Q1
A10: REV-2503-1009 | B10: 45717 | C10: Software Development | D10: West | E10: Crest Healthcare | F10: 915500 | G10: INR | H10: =YEAR(B10) -> 2025 | I10: =TEXT(B10,"mmm") -> Mar | J10: ="Q"&ROUNDUP(MONTH(B10)/3,0) -> Q1
A11: REV-2503-1010 | B11: 45717 | C11: Website Development | D11: East | E11: Evergreen Finance | F11: 534300 | G11: INR | H11: =YEAR(B11) -> 2025 | I11: =TEXT(B11,"mmm") -> Mar | J11: ="Q"&ROUNDUP(MONTH(B11)/3,0) -> Q1
A12: REV-2503-1011 | B12: 45717 | C12: AMC & Maintenance | D12: North | E12: Alpha Industries | F12: 446300 | G12: INR | H12: =YEAR(B12) -> 2025 | I12: =TEXT(B12,"mmm") -> Mar | J12: ="Q"&ROUNDUP(MONTH(B12)/3,0) -> Q1
A13: REV-2503-1012 | B13: 45717 | C13: IT Consulting | D13: South | E13: Crest Healthcare | F13: 366900 | G13: INR | H13: =YEAR(B13) -> 2025 | I13: =TEXT(B13,"mmm") -> Mar | J13: ="Q"&ROUNDUP(MONTH(B13)/3,0) -> Q1
... A49: REV-2512-1048 | B49: 45992 | C49: IT Consulting | D49: West | E49: FutureTech | F49: 511400 | G49: INR | H49: =YEAR(B49) -> 2025 | I49: =TEXT(B49,"mmm") -> Dec | J49: ="Q"&ROUNDUP(MONTH(B49)/3,0) -> Q4

Sheet Expenses
A1: Expense_ID | B1: Date | C1: Department | D1: Category | E1: Actual_Expense | F1: Currency | G1: Year | H1: Month | I1: Quarter
A2: EXP-2501-2001 | B2: 45658 | C2: Engineering | D2: Employee Costs | E2: 705600 | F2: INR | G2: =YEAR(B2) -> 2025 | H2: =TEXT(B2,"mmm") -> Jan | I2: =IFERROR("Q"&ROUNDUP(MONTH(B2)/3,0)," ") -> Q1
A3: EXP-2501-2002 | B3: 45658 | C3: IT | D3: Infrastructure | E3: 161700 | F3: INR | G3: =YEAR(B3) -> 2025 | H3: =TEXT(B3,"mmm") -> Jan | I3: =IFERROR("Q"&ROUNDUP(MONTH(B2)/3,0)," ") -> Q1
A4: EXP-2501-2003 | B4: 45658 | C4: Sales & Marketing | D4: Marketing | E4: 137200 | F4: INR | G4: =YEAR(B4) -> 2025 | H4: =TEXT(B4,"mmm") -> Jan | I4: =IFERROR("Q"&ROUNDUP(MONTH(B2)/3,0)," ") -> Q1
A5: EXP-2501-2004 | B5: 45658 | C5: Operations | D5: Travel | E5: 63700 | F5: INR | G5: =YEAR(B5) -> 2025 | H5: =TEXT(B5,"mmm") -> Jan | I5: =IFERROR("Q"&ROUNDUP(MONTH(B3)/3,0)," ") -> Q1
A6: EXP-2501-2005 | B6: 45658 | C6: HR | D6: Software | E6: 112700 | F6: INR | G6: =YEAR(B6) -> 2025 | H6: =TEXT(B6,"mmm") -> Jan | I6: =IFERROR("Q"&ROUNDUP(MONTH(B4)/3,0)," ") -> Q1
A7: EXP-2501-2006 | B7: 45658 | C7: Finance & Admin | D7: Operations | E7: 93100 | F7: INR | G7: =YEAR(B7) -> 2025 | H7: =TEXT(B7,"mmm") -> Jan | I7: =IFERROR("Q"&ROUNDUP(MONTH(B5)/3,0)," ") -> Q1
A8: EXP-2501-2007 | B8: 45658 | C8: Engineering | D8: Utilities | E8: 41200 | F8: INR | G8: =YEAR(B8) -> 2025 | H8: =TEXT(B8,"mmm") -> Jan | I8: =IFERROR("Q"&ROUNDUP(MONTH(B6)/3,0)," ") -> Q1
A9: EXP-2501-2008 | B9: 45658 | C9: IT | D9: Administration | E9: 51000 | F9: INR | G9: =YEAR(B9) -> 2025 | H9: =TEXT(B9,"mmm") -> Jan | I9: =IFERROR("Q"&ROUNDUP(MONTH(B7)/3,0)," ") -> Q1
A10: EXP-2502-2009 | B10: 45689 | C10: Engineering | D10: Employee Costs | E10: 735900 | F10: INR | G10: =YEAR(B10) -> 2025 | H10: =TEXT(B10,"mmm") -> Feb | I10: =IFERROR("Q"&ROUNDUP(MONTH(B8)/3,0)," ") -> Q1
A11: EXP-2502-2010 | B11: 45689 | C11: IT | D11: Infrastructure | E11: 168600 | F11: INR | G11: =YEAR(B11) -> 2025 | H11: =TEXT(B11,"mmm") -> Feb | I11: =IFERROR("Q"&ROUNDUP(MONTH(B9)/3,0)," ") -> Q1
A12: EXP-2502-2011 | B12: 45689 | C12: Sales & Marketing | D12: Marketing | E12: 143100 | F12: INR | G12: =YEAR(B12) -> 2025 | H12: =TEXT(B12,"mmm") -> Feb | I12: =IFERROR("Q"&ROUNDUP(MONTH(B10)/3,0)," ") -> Q1
A13: EXP-2502-2012 | B13: 45689 | C13: Operations | D13: Travel | E13: 66400 | F13: INR | G13: =YEAR(B13) -> 2025 | H13: =TEXT(B13,"mmm") -> Feb | I13: =IFERROR("Q"&ROUNDUP(MONTH(B11)/3,0)," ") -> Q1
A14: EXP-2502-2013 | B14: 45689 | C14: HR | D14: Software | E14: 117500 | F14: INR | G14: =YEAR(B14) -> 2025 | H14: =TEXT(B14,"mmm") -> Feb | I14: =IFERROR("Q"&ROUNDUP(MONTH(B12)/3,0)," ") -> Q1
A15: EXP-2502-2014 | B15: 45689 | C15: Finance & Admin | D15: Operations | E15: 97100 | F15: INR | G15: =YEAR(B15) -> 2025 | H15: =TEXT(B15,"mmm") -> Feb | I15: =IFERROR("Q"&ROUNDUP(MONTH(B13)/3,0)," ") -> Q1
... A97: EXP-2512-2096 | B97: 45992 | C97: IT | D97: Administration | E97: 64800 | F97: INR | G97: =YEAR(B97) -> 2025 | H97: =TEXT(B97,"mmm") -> Dec | I97: =IFERROR("Q"&ROUNDUP(MONTH(B95)/3,0)," ") -> Q4

Sheet Budget
A1: Department | B1: Annual_Budget | C1: Annual_Actual | D1: Variance | E1: Utilization_% | F1: Utilization % | G1: Status
A2: Engineering | B2: 10809700 | C2: 10009000 | D2: =C2-B2 -> -800700 | E2: 0.92592764 | F2: =IFERROR(C2/B2,0) -> 0.92592764 | G2: =IF(F2>1,"OVER BUDGET",IF(F2>=0.9,"WATCH","OK")) -> WATCH
A3: IT | B3: 3135800 | C3: 2850700 | D3: =C3-B3 -> -285100 | E3: 0.90908221 | F3: =IFERROR(C3/B3,0) -> 0.90908221 | G3: =IF(F3>1,"OVER BUDGET",IF(F3>=0.9,"WATCH","OK")) -> WATCH
A4: Sales & Marketing | B4: 1931100 | C4: 1839100 | D4: =C4-B4 -> -92000 | E4: 0.95235876 | F4: =IFERROR(C4/B4,0) -> 0.95235876 | G4: =IF(F4>1,"OVER BUDGET",IF(F4>=0.9,"WATCH","OK")) -> WATCH
A5: Operations | B5: 913700 | C5: 853900 | D5: =C5-B5 -> -59800 | E5: 0.93455182 | F5: =IFERROR(C5/B5,0) -> 0.93455182 | G5: =IF(F5>1,"OVER BUDGET",IF(F5>=0.9,"WATCH","OK")) -> WATCH
A6: HR | B6: 1691800 | C6: 1510500 | D6: =C6-B6 -> -181300 | E6: 0.89283603 | F6: =IFERROR(C6/B6,0) -> 0.89283603 | G6: =IF(F6>1,"OVER BUDGET",IF(F6>=0.9,"WATCH","OK")) -> OK
A7: Finance & Admin | B7: 1322800 | C7: 1247900 | D7: =C7-B7 -> -74900 | E7: 0.94337768 | F7: =IFERROR(C7/B7,0) -> 0.94337768 | G7: =IF(F7>1,"OVER BUDGET",IF(F7>=0.9,"WATCH","OK")) -> WATCH

Sheet Monthly_Budget
A1: Month | B1: Department | C1: Budget
A2: 45658 | B2: Engineering | C2: 827272.96
A3: 45689 | B3: Engineering | C3: 860363.88
A4: 45717 | B4: Engineering | C4: 882424.49
A5: 45748 | B5: Engineering | C5: 893454.8
A6: 45778 | B6: Engineering | C6: 904485.1
A7: 45809 | B7: Engineering | C7: 915515.41
A8: 45839 | B8: Engineering | C8: 926545.71
A9: 45870 | B9: Engineering | C9: 904485.1
A10: 45901 | B10: Engineering | C10: 915515.41
A11: 45931 | B11: Engineering | C11: 926545.71
A12: 45962 | B12: Engineering | C12: 926545.71
A13: 45992 | B13: Engineering | C13: 926545.71
... A73: 45992 | B73: Finance & Admin | C73: 113382.86

Sheet Variance
A1: Month | B1: Department | C1: Budget | D1: Actual_Expense | E1: Variance | F1: Utilization_%
A2: 45658 | B2: Engineering | C2: 827272.96 | D2: 746800 | E2: =C2-D2 -> 80472.96 | F2: =D2/C2 -> 0.90272502
A3: 45689 | B3: Engineering | C3: 860363.88 | D3: 778800 | E3: =C3-D3 -> 81563.88 | F3: =D3/C3 -> 0.90519839
A4: 45717 | B4: Engineering | C4: 882424.49 | D4: 780300 | E4: =C4-D4 -> 102124.49 | F4: =D4/C4 -> 0.8842683
A5: 45748 | B5: Engineering | C5: 893454.8 | D5: 813100 | E5: =C5-D5 -> 80354.8 | F5: =D5/C5 -> 0.91006283
A6: 45778 | B6: Engineering | C6: 904485.1 | D6: 790600 | E6: =C6-D6 -> 113885.1 | F6: =D6/C6 -> 0.87408847
A7: 45809 | B7: Engineering | C7: 915515.41 | D7: 823900 | E7: =C7-D7 -> 91615.41 | F7: =D7/C7 -> 0.89993024
A8: 45839 | B8: Engineering | C8: 926545.71 | D8: 849500 | E8: =C8-D8 -> 77045.71 | F8: =D8/C8 -> 0.91684629
A9: 45870 | B9: Engineering | C9: 904485.1 | D9: 826000 | E9: =C9-D9 -> 78485.1 | F9: =D9/C9 -> 0.91322676
A10: 45901 | B10: Engineering | C10: 915515.41 | D10: 876900 | E10: =C10-D10 -> 38615.41 | F10: =D10/C10 -> 0.95782113
A11: 45931 | B11: Engineering | C11: 926545.71 | D11: 861200 | E11: =C11-D11 -> 65345.71 | F11: =D11/C11 -> 0.92947384
A12: 45962 | B12: Engineering | C12: 926545.71 | D12: 913100 | E12: =C12-D12 -> 13445.71 | F12: =D12/C12 -> 0.98548835
A13: 45992 | B13: Engineering | C13: 926545.71 | D13: 948800 | E13: =C13-D13 -> -22254.29 | F13: =D13/C13 -> 1.0240186
... A73: 45992 | B73: Finance & Admin | C73: 113382.86 | D73: 118300 | E73: =C73-D73 -> -4917.14 | F73: =D73/C73 -> 1.0433676

Sheet CashFlow
A1: Month | B1: Opening_Cash | C1: Customer_Collections | D1: Other_Operating_Inflows | E1: Investments | F1: Loan_Draw | G1: Total_Inflows | H1: Operating_Expenses | I1: Asset_Purchases | J1: Debt_Repayment | K1: Total_Outflows | L1: Closing_Cash
A2: 45658 | B2: 5000000 | C2: 2049913 | D2: 61794 | E2: 0 | F2: 0 | G2: 2111707 | H2: 1366200 | I2: 0 | J2: 100000 | K2: 1466200 | L2: =B2+G2-K2 -> 5645507
A3: 45689 | B3: 5645507 | C3: 2152260 | D3: 64809 | E3: 0 | F3: 0 | G3: 2217069 | H3: 1424700 | I3: 0 | J3: 100000 | K3: 1524700 | L3: =B3+G3-K3 -> 6337876
A4: 45717 | B4: 6337876 | C4: 2254784 | D4: 67890 | E4: 150000 | F4: 0 | G4: 2472674 | H4: 1427600 | I4: 0 | J4: 100000 | K4: 1527600 | L4: =B4+G4-K4 -> 7282950
A5: 45748 | B5: 7282950 | C5: 2338256 | D5: 70344 | E5: 0 | F5: 0 | G5: 2408600 | H5: 1487600 | I5: 0 | J5: 100000 | K5: 1587600 | L5: =B5+G5-K5 -> 8103950
A6: 45778 | B6: 8103950 | C6: 2421436 | D6: 72843 | E6: 0 | F6: 0 | G6: 2494279 | H6: 1446400 | I6: 250000 | J6: 100000 | K6: 1796400 | L6: =B6+G6-K6 -> 8801829
A7: 45809 | B7: 8801829 | C7: 2527828 | D7: 76095 | E7: 0 | F7: 0 | G7: 2603923 | H7: 1507200 | I7: 0 | J7: 100000 | K7: 1607200 | L7: =B7+G7-K7 -> 9798552
A8: 45839 | B8: 9798552 | C8: 2527484 | D8: 75801 | E8: 0 | F8: 0 | G8: 2603285 | H8: 1554200 | I8: 0 | J8: 100000 | K8: 1654200 | L8: =B8+G8-K8 -> 10747637
A9: 45870 | B9: 10747637 | C9: 2628820 | D9: 79131 | E9: 150000 | F9: 0 | G9: 2857951 | H9: 1511300 | I9: 0 | J9: 100000 | K9: 1611300 | L9: =B9+G9-K9 -> 11994288
A10: 45901 | B10: 11994288 | C10: 2718844 | D10: 81777 | E10: 0 | F10: 0 | G10: 2800621 | H10: 1604100 | I10: 0 | J10: 100000 | K10: 1704100 | L10: =B10+G10-K10 -> 13090809
A11: 45931 | B11: 13090809 | C11: 2808516 | D11: 84471 | E11: 0 | F11: 0 | G11: 2892987 | H11: 1575600 | I11: 250000 | J11: 100000 | K11: 1925600 | L11: =B11+G11-K11 -> 14058196
A12: 45962 | B12: 14058196 | C12: 2946432 | D12: 88734 | E12: 0 | F12: 0 | G12: 3035166 | H12: 1670400 | I12: 0 | J12: 100000 | K12: 1770400 | L12: =B12+G12-K12 -> 15322962
A13: 45992 | B13: 15322962 | C13: 3138764 | D13: 94635 | E13: 0 | F13: 0 | G13: 3233399 | H13: 1735800 | I13: 0 | J13: 100000 | K13: 1835800 | L13: =B13+G13-K13 -> 16720561

Sheet AR_Aging
A1: Invoice_Number | B1: Customer | C1: Invoice_Date | D1: Due_Date | E1: Invoice_Amount | F1: Paid_Amount | G1: Outstanding_Amount | H1: Payment_Status | I1: Days_Overdue | J1: Aging_Bucket | K1: Invoice ID | L1: Invoice Date | M1: Due Date | N1: Invoice Amount | O1: Amount Received | P1: Outstanding | Q1: Days Overdue | R1: Aging Bucket | S1: Status
A2: AR-5001 | B2: Alpha Industries | C2: 45658 | D2: 45688 | E2: 150000 | F2: 150000 | G2: 0 | H2: Paid | I2: 0 | J2: 0-30 | K2: =A2 -> AR-5001 | L2: =C2 -> 45658 | M2: =D2 -> 45688 | N2: =E2 -> 150000 | O2: =N2 -> 150000 | P2: =MAX(0,N2-O2) -> 0 | Q2: =IF(P2=0,0,MAX(0,TODAY()-M2)) -> 0 | R2: =IF(P2=0,"Paid",IF(Q2<=30,"0-30",IF(Q2<=60,"31-60",IF(Q2<=90,"61-90","90+")))) -> Paid | S2: =IF(P2=0,"Paid",IF(Q2>90,"Critical",IF(Q2>60,"Overdue","Open"))) -> Paid
A3: AR-5002 | B3: Bright Retail | C3: 45658 | D3: 45688 | E3: 185000 | F3: 157200 | G3: 27800 | H3: Partially Paid | I3: 334 | J3: 90+ | K3: =A3 -> AR-5002 | L3: =C3 -> 45658 | M3: =D3 -> 45688 | N3: =E3 -> 185000 | O3: =N3 -> 185000 | P3: =MAX(0,N3-O3) -> 0 | Q3: =IF(P3=0,0,MAX(0,TODAY()-M3)) -> 0 | R3: =IF(P3=0,"Paid",IF(Q3<=30,"0-30",IF(Q3<=60,"31-60",IF(Q3<=90,"61-90","90+")))) -> Paid | S3: =IF(P3=0,"Paid",IF(Q3>90,"Critical",IF(Q3>60,"Overdue","Open"))) -> Paid
A4: AR-5003 | B4: Crest Healthcare | C4: 45658 | D4: 45688 | E4: 220000 | F4: 132000 | G4: 88000 | H4: Partially Paid | I4: 334 | J4: 90+ | K4: =A4 -> AR-5003 | L4: =C4 -> 45658 | M4: =D4 -> 45688 | N4: =E4 -> 220000 | O4: =N4 -> 220000 | P4: =MAX(0,N4-O4) -> 0 | Q4: =IF(P4=0,0,MAX(0,TODAY()-M4)) -> 0 | R4: =IF(P4=0,"Paid",IF(Q4<=30,"0-30",IF(Q4<=60,"31-60",IF(Q4<=90,"61-90","90+")))) -> Paid | S4: =IF(P4=0,"Paid",IF(Q4>90,"Critical",IF(Q4>60,"Overdue","Open"))) -> Paid
A5: AR-5004 | B5: Delta Logistics | C5: 45658 | D5: 45688 | E5: 255000 | F5: 76500 | G5: 178500 | H5: Partially Paid | I5: 334 | J5: 90+ | K5: =A5 -> AR-5004 | L5: =C5 -> 45658 | M5: =D5 -> 45688 | N5: =E5 -> 255000 | O5: =N5 -> 255000 | P5: =MAX(0,N5-O5) -> 0 | Q5: =IF(P5=0,0,MAX(0,TODAY()-M5)) -> 0 | R5: =IF(P5=0,"Paid",IF(Q5<=30,"0-30",IF(Q5<=60,"31-60",IF(Q5<=90,"61-90","90+")))) -> Paid | S5: =IF(P5=0,"Paid",IF(Q5>90,"Critical",IF(Q5>60,"Overdue","Open"))) -> Paid
A6: AR-5005 | B6: Evergreen Finance | C6: 45658 | D6: 45688 | E6: 290000 | F6: 0 | G6: 290000 | H6: Unpaid | I6: 334 | J6: 90+ | K6: =A6 -> AR-5005 | L6: =C6 -> 45658 | M6: =D6 -> 45688 | N6: =E6 -> 290000 | O6: =N6 -> 290000 | P6: =MAX(0,N6-O6) -> 0 | Q6: =IF(P6=0,0,MAX(0,TODAY()-M6)) -> 0 | R6: =IF(P6=0,"Paid",IF(Q6<=30,"0-30",IF(Q6<=60,"31-60",IF(Q6<=90,"61-90","90+")))) -> Paid | S6: =IF(P6=0,"Paid",IF(Q6>90,"Critical",IF(Q6>60,"Overdue","Open"))) -> Paid
A7: AR-5006 | B7: Bright Retail | C7: 45689 | D7: 45719 | E7: 160000 | F7: 136000 | G7: 24000 | H7: Partially Paid | I7: 303 | J7: 90+ | K7: =A7 -> AR-5006 | L7: =C7 -> 45689 | M7: =D7 -> 45719 | N7: =E7 -> 160000 | O7: =N7 -> 160000 | P7: =MAX(0,N7-O7) -> 0 | Q7: =IF(P7=0,0,MAX(0,TODAY()-M7)) -> 0 | R7: =IF(P7=0,"Paid",IF(Q7<=30,"0-30",IF(Q7<=60,"31-60",IF(Q7<=90,"61-90","90+")))) -> Paid | S7: =IF(P7=0,"Paid",IF(Q7>90,"Critical",IF(Q7>60,"Overdue","Open"))) -> Paid
A8: AR-5007 | B8: Crest Healthcare | C8: 45689 | D8: 45719 | E8: 195000 | F8: 117000 | G8: 78000 | H8: Partially Paid | I8: 303 | J8: 90+ | K8: =A8 -> AR-5007 | L8: =C8 -> 45689 | M8: =D8 -> 45719 | N8: =E8 -> 195000 | O8: =N8 -> 195000 | P8: =MAX(0,N8-O8) -> 0 | Q8: =IF(P8=0,0,MAX(0,TODAY()-M8)) -> 0 | R8: =IF(P8=0,"Paid",IF(Q8<=30,"0-30",IF(Q8<=60,"31-60",IF(Q8<=90,"61-90","90+")))) -> Paid | S8: =IF(P8=0,"Paid",IF(Q8>90,"Critical",IF(Q8>60,"Overdue","Open"))) -> Paid
A9: AR-5008 | B9: Delta Logistics | C9: 45689 | D9: 45719 | E9: 230000 | F9: 69000 | G9: 161000 | H9: Partially Paid | I9: 303 | J9: 90+ | K9: =A9 -> AR-5008 | L9: =C9 -> 45689 | M9: =D9 -> 45719 | N9: =E9 -> 230000 | O9: =N9 -> 230000 | P9: =MAX(0,N9-O9) -> 0 | Q9: =IF(P9=0,0,MAX(0,TODAY()-M9)) -> 0 | R9: =IF(P9=0,"Paid",IF(Q9<=30,"0-30",IF(Q9<=60,"31-60",IF(Q9<=90,"61-90","90+")))) -> Paid | S9: =IF(P9=0,"Paid",IF(Q9>90,"Critical",IF(Q9>60,"Overdue","Open"))) -> Paid
A10: AR-5009 | B10: Evergreen Finance | C10: 45689 | D10: 45719 | E10: 265000 | F10: 0 | G10: 265000 | H10: Unpaid | I10: 303 | J10: 90+ | K10: =A10 -> AR-5009 | L10: =C10 -> 45689 | M10: =D10 -> 45719 | N10: =E10 -> 265000 | O10: =N10 -> 265000 | P10: =MAX(0,N10-O10) -> 0 | Q10: =IF(P10=0,0,MAX(0,TODAY()-M10)) -> 0 | R10: =IF(P10=0,"Paid",IF(Q10<=30,"0-30",IF(Q10<=60,"31-60",IF(Q10<=90,"61-90","90+")))) -> Paid | S10: =IF(P10=0,"Paid",IF(Q10>90,"Critical",IF(Q10>60,"Overdue","Open"))) -> Paid
A11: AR-5010 | B11: FutureTech | C11: 45689 | D11: 45719 | E11: 300000 | F11: 300000 | G11: 0 | H11: Paid | I11: 0 | J11: 0-30 | K11: =A11 -> AR-5010 | L11: =C11 -> 45689 | M11: =D11 -> 45719 | N11: =E11 -> 300000 | O11: =N11 -> 300000 | P11: =MAX(0,N11-O11) -> 0 | Q11: =IF(P11=0,0,MAX(0,TODAY()-M11)) -> 0 | R11: =IF(P11=0,"Paid",IF(Q11<=30,"0-30",IF(Q11<=60,"31-60",IF(Q11<=90,"61-90","90+")))) -> Paid | S11: =IF(P11=0,"Paid",IF(Q11>90,"Critical",IF(Q11>60,"Overdue","Open"))) -> Paid
A12: AR-5011 | B12: Crest Healthcare | C12: 45717 | D12: 45747 | E12: 170000 | F12: 102000 | G12: 68000 | H12: Partially Paid | I12: 275 | J12: 90+ | K12: =A12 -> AR-5011 | L12: =C12 -> 45717 | M12: =D12 -> 45747 | N12: =E12 -> 170000 | O12: =N12 -> 170000 | P12: =MAX(0,N12-O12) -> 0 | Q12: =IF(P12=0,0,MAX(0,TODAY()-M12)) -> 0 | R12: =IF(P12=0,"Paid",IF(Q12<=30,"0-30",IF(Q12<=60,"31-60",IF(Q12<=90,"61-90","90+")))) -> Paid | S12: =IF(P12=0,"Paid",IF(Q12>90,"Critical",IF(Q12>60,"Overdue","Open"))) -> Paid
A13: AR-5012 | B13: Delta Logistics | C13: 45717 | D13: 45747 | E13: 205000 | F13: 61500 | G13: 143500 | H13: Partially Paid | I13: 275 | J13: 90+ | K13: =A13 -> AR-5012 | L13: =C13 -> 45717 | M13: =D13 -> 45747 | N13: =E13 -> 205000 | O13: =N13 -> 205000 | P13: =MAX(0,N13-O13) -> 0 | Q13: =IF(P13=0,0,MAX(0,TODAY()-M13)) -> 0 | R13: =IF(P13=0,"Paid",IF(Q13<=30,"0-30",IF(Q13<=60,"31-60",IF(Q13<=90,"61-90","90+")))) -> Paid | S13: =IF(P13=0,"Paid",IF(Q13>90,"Critical",IF(Q13>60,"Overdue","Open"))) -> Paid
... A61: AR-5060 | B61: Delta Logistics | C61: 45992 | D61: 46022 | E61: 400000 | F61: 400000 | G61: 0 | H61: Paid | I61: 0 | J61: 0-30 | K61: =A61 -> AR-5060 | L61: =C61 -> 45992 | M61: =D61 -> 46022 | N61: =E61 -> 400000 | O61: =N61 -> 400000 | P61: =MAX(0,N61-O61) -> 0 | Q61: =IF(P61=0,0,MAX(0,TODAY()-M61)) -> 0 | R61: =IF(P61=0,"Paid",IF(Q61<=30,"0-30",IF(Q61<=60,"31-60",IF(Q61<=90,"61-90","90+")))) -> Paid | S61: =IF(P61=0,"Paid",IF(Q61>90,"Critical",IF(Q61>60,"Overdue","Open"))) -> Paid
A64: AR AGING SUMMARY
A65: Total Invoice Amount | B65: =SUM(N2:N64) -> 16500000
A66: Total Received | B66: =SUM(O2:O64) -> 16500000
A67: Total Outstanding | B67: =SUM(P2:P64) -> 0
A68: 0-30 | B68: =SUMIF(R2:R64,"0-30",P2:P64) -> 0
A69: 31-60 | B69: =SUMIF(R2:R64,"31-60",P2:P64) -> 0
A70: 61-90 | B70: =SUMIF(R2:R64,"61-90",P2:P64) -> 0
A71: 90+ | B71: =SUMIF(R2:R64,"90+",P2:P64) -> 0

Sheet AP_Aging
A1: Bill_Number | B1: Vendor | C1: Bill_Date | D1: Due_Date | E1: Bill_Amount | F1: Paid_Amount | G1: Outstanding_Amount | H1: Payment_Status | I1: Days_Overdue | J1: Aging_Bucket | K1: Bill ID | L1: Supplier | M1: Bill Date | N1: Due Date | O1: Bill Amount | P1: Amount Paid | Q1: Outstanding | R1: Days Overdue | S1: Aging Bucket | T1: Status
A2: AP-7001 | B2: CloudNet | C2: 45658 | D2: 45688 | E2: 120000 | F2: 120000 | G2: 0 | H2: Paid | I2: 0 | J2: 0-30 | K2: =A2 -> AP-7001 | L2: =B2 -> CloudNet | M2: =C2 -> 45658 | N2: =D2 -> 45688 | O2: =E2 -> 120000 | P2: =O2 -> 120000 | Q2: =MAX(0,O2-P2) -> 0 | R2: =IF(Q2=0,0,MAX(0,TODAY()-N2)) -> 0 | S2: =IF(Q2=0,"Paid",IF(R2<=30,"0-30",IF(R2<=60,"31-60",IF(R2<=90,"61-90","90+")))) -> Paid | T2: =IF(Q2=0,"Paid",IF(R2>90,"Critical",IF(R2>60,"Overdue","Open"))) -> Paid
A3: AP-7002 | B3: OfficeHub | C3: 45658 | D3: 45688 | E3: 145000 | F3: 116000 | G3: 29000 | H3: Partially Paid | I3: 334 | J3: 90+ | K3: =A3 -> AP-7002 | L3: =B3 -> OfficeHub | M3: =C3 -> 45658 | N3: =D3 -> 45688 | O3: =E3 -> 145000 | P3: =O3 -> 145000 | Q3: =MAX(0,O3-P3) -> 0 | R3: =IF(Q3=0,0,MAX(0,TODAY()-N3)) -> 0 | S3: =IF(Q3=0,"Paid",IF(R3<=30,"0-30",IF(R3<=60,"31-60",IF(R3<=90,"61-90","90+")))) -> Paid | T3: =IF(Q3=0,"Paid",IF(R3>90,"Critical",IF(R3>60,"Overdue","Open"))) -> Paid
A4: AP-7003 | B4: TravelPro | C4: 45658 | D4: 45688 | E4: 170000 | F4: 85000 | G4: 85000 | H4: Partially Paid | I4: 334 | J4: 90+ | K4: =A4 -> AP-7003 | L4: =B4 -> TravelPro | M4: =C4 -> 45658 | N4: =D4 -> 45688 | O4: =E4 -> 170000 | P4: =O4 -> 170000 | Q4: =MAX(0,O4-P4) -> 0 | R4: =IF(Q4=0,0,MAX(0,TODAY()-N4)) -> 0 | S4: =IF(Q4=0,"Paid",IF(R4<=30,"0-30",IF(R4<=60,"31-60",IF(R4<=90,"61-90","90+")))) -> Paid | T4: =IF(Q4=0,"Paid",IF(R4>90,"Critical",IF(R4>60,"Overdue","Open"))) -> Paid
A5: AP-7004 | B5: SoftWorks | C5: 45658 | D5: 45688 | E5: 195000 | F5: 0 | G5: 195000 | H5: Unpaid | I5: 334 | J5: 90+ | K5: =A5 -> AP-7004 | L5: =B5 -> SoftWorks | M5: =C5 -> 45658 | N5: =D5 -> 45688 | O5: =E5 -> 195000 | P5: =O5 -> 195000 | Q5: =MAX(0,O5-P5) -> 0 | R5: =IF(Q5=0,0,MAX(0,TODAY()-N5)) -> 0 | S5: =IF(Q5=0,"Paid",IF(R5<=30,"0-30",IF(R5<=60,"31-60",IF(R5<=90,"61-90","90+")))) -> Paid | T5: =IF(Q5=0,"Paid",IF(R5>90,"Critical",IF(R5>60,"Overdue","Open"))) -> Paid
A6: AP-7005 | B6: OfficeHub | C6: 45689 | D6: 45719 | E6: 128000 | F6: 102400 | G6: 25600 | H6: Partially Paid | I6: 303 | J6: 90+ | K6: =A6 -> AP-7005 | L6: =B6 -> OfficeHub | M6: =C6 -> 45689 | N6: =D6 -> 45719 | O6: =E6 -> 128000 | P6: =O6 -> 128000 | Q6: =MAX(0,O6-P6) -> 0 | R6: =IF(Q6=0,0,MAX(0,TODAY()-N6)) -> 0 | S6: =IF(Q6=0,"Paid",IF(R6<=30,"0-30",IF(R6<=60,"31-60",IF(R6<=90,"61-90","90+")))) -> Paid | T6: =IF(Q6=0,"Paid",IF(R6>90,"Critical",IF(R6>60,"Overdue","Open"))) -> Paid
A7: AP-7006 | B7: TravelPro | C7: 45689 | D7: 45719 | E7: 153000 | F7: 76500 | G7: 76500 | H7: Partially Paid | I7: 303 | J7: 90+ | K7: =A7 -> AP-7006 | L7: =B7 -> TravelPro | M7: =C7 -> 45689 | N7: =D7 -> 45719 | O7: =E7 -> 153000 | P7: =O7 -> 153000 | Q7: =MAX(0,O7-P7) -> 0 | R7: =IF(Q7=0,0,MAX(0,TODAY()-N7)) -> 0 | S7: =IF(Q7=0,"Paid",IF(R7<=30,"0-30",IF(R7<=60,"31-60",IF(R7<=90,"61-90","90+")))) -> Paid | T7: =IF(Q7=0,"Paid",IF(R7>90,"Critical",IF(R7>60,"Overdue","Open"))) -> Paid
A8: AP-7007 | B8: SoftWorks | C8: 45689 | D8: 45719 | E8: 178000 | F8: 0 | G8: 178000 | H8: Unpaid | I8: 303 | J8: 90+ | K8: =A8 -> AP-7007 | L8: =B8 -> SoftWorks | M8: =C8 -> 45689 | N8: =D8 -> 45719 | O8: =E8 -> 178000 | P8: =O8 -> 178000 | Q8: =MAX(0,O8-P8) -> 0 | R8: =IF(Q8=0,0,MAX(0,TODAY()-N8)) -> 0 | S8: =IF(Q8=0,"Paid",IF(R8<=30,"0-30",IF(R8<=60,"31-60",IF(R8<=90,"61-90","90+")))) -> Paid | T8: =IF(Q8=0,"Paid",IF(R8>90,"Critical",IF(R8>60,"Overdue","Open"))) -> Paid
A9: AP-7008 | B9: UtilityCo | C9: 45689 | D9: 45719 | E9: 203000 | F9: 203000 | G9: 0 | H9: Paid | I9: 0 | J9: 0-30 | K9: =A9 -> AP-7008 | L9: =B9 -> UtilityCo | M9: =C9 -> 45689 | N9: =D9 -> 45719 | O9: =E9 -> 203000 | P9: =O9 -> 203000 | Q9: =MAX(0,O9-P9) -> 0 | R9: =IF(Q9=0,0,MAX(0,TODAY()-N9)) -> 0 | S9: =IF(Q9=0,"Paid",IF(R9<=30,"0-30",IF(R9<=60,"31-60",IF(R9<=90,"61-90","90+")))) -> Paid | T9: =IF(Q9=0,"Paid",IF(R9>90,"Critical",IF(R9>60,"Overdue","Open"))) -> Paid
A10: AP-7009 | B10: TravelPro | C10: 45717 | D10: 45747 | E10: 136000 | F10: 68000 | G10: 68000 | H10: Partially Paid | I10: 275 | J10: 90+ | K10: =A10 -> AP-7009 | L10: =B10 -> TravelPro | M10: =C10 -> 45717 | N10: =D10 -> 45747 | O10: =E10 -> 136000 | P10: =O10 -> 136000 | Q10: =MAX(0,O10-P10) -> 0 | R10: =IF(Q10=0,0,MAX(0,TODAY()-N10)) -> 0 | S10: =IF(Q10=0,"Paid",IF(R10<=30,"0-30",IF(R10<=60,"31-60",IF(R10<=90,"61-90","90+")))) -> Paid | T10: =IF(Q10=0,"Paid",IF(R10>90,"Critical",IF(R10>60,"Overdue","Open"))) -> Paid
A11: AP-7010 | B11: SoftWorks | C11: 45717 | D11: 45747 | E11: 161000 | F11: 0 | G11: 161000 | H11: Unpaid | I11: 275 | J11: 90+ | K11: =A11 -> AP-7010 | L11: =B11 -> SoftWorks | M11: =C11 -> 45717 | N11: =D11 -> 45747 | O11: =E11 -> 161000 | P11: =O11 -> 161000 | Q11: =MAX(0,O11-P11) -> 0 | R11: =IF(Q11=0,0,MAX(0,TODAY()-N11)) -> 0 | S11: =IF(Q11=0,"Paid",IF(R11<=30,"0-30",IF(R11<=60,"31-60",IF(R11<=90,"61-90","90+")))) -> Paid | T11: =IF(Q11=0,"Paid",IF(R11>90,"Critical",IF(R11>60,"Overdue","Open"))) -> Paid
A12: AP-7011 | B12: UtilityCo | C12: 45717 | D12: 45747 | E12: 186000 | F12: 186000 | G12: 0 | H12: Paid | I12: 0 | J12: 0-30 | K12: =A12 -> AP-7011 | L12: =B12 -> UtilityCo | M12: =C12 -> 45717 | N12: =D12 -> 45747 | O12: =E12 -> 186000 | P12: =O12 -> 186000 | Q12: =MAX(0,O12-P12) -> 0 | R12: =IF(Q12=0,0,MAX(0,TODAY()-N12)) -> 0 | S12: =IF(Q12=0,"Paid",IF(R12<=30,"0-30",IF(R12<=60,"31-60",IF(R12<=90,"61-90","90+")))) -> Paid | T12: =IF(Q12=0,"Paid",IF(R12>90,"Critical",IF(R12>60,"Overdue","Open"))) -> Paid
A13: AP-7012 | B13: InfraServe | C13: 45717 | D13: 45747 | E13: 211000 | F13: 168800 | G13: 42200 | H13: Partially Paid | I13: 275 | J13: 90+ | K13: =A13 -> AP-7012 | L13: =B13 -> InfraServe | M13: =C13 -> 45717 | N13: =D13 -> 45747 | O13: =E13 -> 211000 | P13: =O13 -> 211000 | Q13: =MAX(0,O13-P13) -> 0 | R13: =IF(Q13=0,0,MAX(0,TODAY()-N13)) -> 0 | S13: =IF(Q13=0,"Paid",IF(R13<=30,"0-30",IF(R13<=60,"31-60",IF(R13<=90,"61-90","90+")))) -> Paid | T13: =IF(Q13=0,"Paid",IF(R13>90,"Critical",IF(R13>60,"Overdue","Open"))) -> Paid
... A49: AP-7048 | B49: TravelPro | C49: 45992 | D49: 46022 | E49: 283000 | F49: 141500 | G49: 141500 | H49: Partially Paid | I49: 0 | J49: 0-30 | K49: =A49 -> AP-7048 | L49: =B49 -> TravelPro | M49: =C49 -> 45992 | N49: =D49 -> 46022 | O49: =E49 -> 283000 | P49: =O49 -> 283000 | Q49: =MAX(0,O49-P49) -> 0 | R49: =IF(Q49=0,0,MAX(0,TODAY()-N49)) -> 0 | S49: =IF(Q49=0,"Paid",IF(R49<=30,"0-30",IF(R49<=60,"31-60",IF(R49<=90,"61-90","90+")))) -> Paid | T49: =IF(Q49=0,"Paid",IF(R49>90,"Critical",IF(R49>60,"Overdue","Open"))) -> Paid
A52: AP AGING SUMMARY
A53: Total Bill Amount | B53: =SUM(O2:O52) -> 9672000
A54: Total Paid | B54: =SUM(P2:P52) -> 9672000
A55: Total Outstanding | B55: =SUM(Q2:Q52) -> 0
A56: 0-30 | B56: =SUMIF(S2:S52,"0-30",Q2:Q52) -> 0
A57: 31-60 | B57: =SUMIF(S2:S52,"31-60",Q2:Q52) -> 0
A58: 61-90 | B58: =SUMIF(S2:S52,"61-90",Q2:Q52) -> 0
A59: 90+ | B59: =SUMIF(S2:S52,"90+",Q2:Q52) -> 0

Sheet Working_Capital
A1: Month | B1: Cash | C1: AR | D1: Inventory | E1: Current_Assets | F1: Current_Liabilities | G1: Working_Capital | H1: Current_Ratio | I1: Quick_Ratio
A2: Month | B2: Current Assets | C2: Current Liabilities | D2: Working Capital | E2: Quick Assets | F2: Inventory | G2: Current Ratio | H2: Quick Ratio | I2: AR Days | J2: AP Days
A3: =DATE(2025,1,1) -> 45658 | B3: =SUM(AR_Aging!$G:$G)+INDEX(CashFlow!$L:$L,MATCH(A3,CashFlow!$A:$A,0)) -> 13170307 | C3: =SUM(AP_Aging!$G:$G) -> 4110600 | D3: =B3-C3 -> 9059707 | E3: =B3-F3 -> 13170307 | F3: =0 -> 0 | G3: =IFERROR(B3/C3,0) -> 3.2039865 | H3: =IFERROR(E3/C3,0) -> 3.2039865 | I3: =IFERROR(SUM(AR_Aging!$G:$G)/SUM(Monthly_PnL!$B:$B)*365,0) -> 89.724934 | J3: =IFERROR(SUM(AP_Aging!$G:$G)/SUM(Monthly_PnL!$E:$E)*365,0) -> 81.937677
A4: =DATE(2025,2,1) -> 45689 | B4: =SUM(AR_Aging!$G:$G)+INDEX(CashFlow!$L:$L,MATCH(A4,CashFlow!$A:$A,0)) -> 13862676 | C4: =SUM(AP_Aging!$G:$G) -> 4110600 | D4: =B4-C4 -> 9752076 | E4: =B4-F4 -> 13862676 | F4: =0 -> 0 | G4: =IFERROR(B4/C4,0) -> 3.3724215 | H4: =IFERROR(E4/C4,0) -> 3.3724215 | I4: =IFERROR(SUM(AR_Aging!$G:$G)/SUM(Monthly_PnL!$B:$B)*365,0) -> 89.724934 | J4: =IFERROR(SUM(AP_Aging!$G:$G)/SUM(Monthly_PnL!$E:$E)*365,0) -> 81.937677
A5: =DATE(2025,3,1) -> 45717 | B5: =SUM(AR_Aging!$G:$G)+INDEX(CashFlow!$L:$L,MATCH(A5,CashFlow!$A:$A,0)) -> 14807750 | C5: =SUM(AP_Aging!$G:$G) -> 4110600 | D5: =B5-C5 -> 10697150 | E5: =B5-F5 -> 14807750 | F5: =0 -> 0 | G5: =IFERROR(B5/C5,0) -> 3.602333 | H5: =IFERROR(E5/C5,0) -> 3.602333 | I5: =IFERROR(SUM(AR_Aging!$G:$G)/SUM(Monthly_PnL!$B:$B)*365,0) -> 89.724934 | J5: =IFERROR(SUM(AP_Aging!$G:$G)/SUM(Monthly_PnL!$E:$E)*365,0) -> 81.937677
A6: =DATE(2025,4,1) -> 45748 | B6: =SUM(AR_Aging!$G:$G)+INDEX(CashFlow!$L:$L,MATCH(A6,CashFlow!$A:$A,0)) -> 15628750 | C6: =SUM(AP_Aging!$G:$G) -> 4110600 | D6: =B6-C6 -> 11518150 | E6: =B6-F6 -> 15628750 | F6: =0 -> 0 | G6: =IFERROR(B6/C6,0) -> 3.8020605 | H6: =IFERROR(E6/C6,0) -> 3.8020605 | I6: =IFERROR(SUM(AR_Aging!$G:$G)/SUM(Monthly_PnL!$B:$B)*365,0) -> 89.724934 | J6: =IFERROR(SUM(AP_Aging!$G:$G)/SUM(Monthly_PnL!$E:$E)*365,0) -> 81.937677
A7: =DATE(2025,5,1) -> 45778 | B7: =SUM(AR_Aging!$G:$G)+INDEX(CashFlow!$L:$L,MATCH(A7,CashFlow!$A:$A,0)) -> 16326629 | C7: =SUM(AP_Aging!$G:$G) -> 4110600 | D7: =B7-C7 -> 12216029 | E7: =B7-F7 -> 16326629 | F7: =0 -> 0 | G7: =IFERROR(B7/C7,0) -> 3.971836 | H7: =IFERROR(E7/C7,0) -> 3.971836 | I7: =IFERROR(SUM(AR_Aging!$G:$G)/SUM(Monthly_PnL!$B:$B)*365,0) -> 89.724934 | J7: =IFERROR(SUM(AP_Aging!$G:$G)/SUM(Monthly_PnL!$E:$E)*365,0) -> 81.937677
A8: =DATE(2025,6,1) -> 45809 | B8: =SUM(AR_Aging!$G:$G)+INDEX(CashFlow!$L:$L,MATCH(A8,CashFlow!$A:$A,0)) -> 17323352 | C8: =SUM(AP_Aging!$G:$G) -> 4110600 | D8: =B8-C8 -> 13212752 | E8: =B8-F8 -> 17323352 | F8: =0 -> 0 | G8: =IFERROR(B8/C8,0) -> 4.2143123 | H8: =IFERROR(E8/C8,0) -> 4.2143123 | I8: =IFERROR(SUM(AR_Aging!$G:$G)/SUM(Monthly_PnL!$B:$B)*365,0) -> 89.724934 | J8: =IFERROR(SUM(AP_Aging!$G:$G)/SUM(Monthly_PnL!$E:$E)*365,0) -> 81.937677
A9: =DATE(2025,7,1) -> 45839 | B9: =SUM(AR_Aging!$G:$G)+INDEX(CashFlow!$L:$L,MATCH(A9,CashFlow!$A:$A,0)) -> 18272437 | C9: =SUM(AP_Aging!$G:$G) -> 4110600 | D9: =B9-C9 -> 14161837 | E9: =B9-F9 -> 18272437 | F9: =0 -> 0 | G9: =IFERROR(B9/C9,0) -> 4.4451995 | H9: =IFERROR(E9/C9,0) -> 4.4451995 | I9: =IFERROR(SUM(AR_Aging!$G:$G)/SUM(Monthly_PnL!$B:$B)*365,0) -> 89.724934 | J9: =IFERROR(SUM(AP_Aging!$G:$G)/SUM(Monthly_PnL!$E:$E)*365,0) -> 81.937677
A10: =DATE(2025,8,1) -> 45870 | B10: =SUM(AR_Aging!$G:$G)+INDEX(CashFlow!$L:$L,MATCH(A10,CashFlow!$A:$A,0)) -> 19519088 | C10: =SUM(AP_Aging!$G:$G) -> 4110600 | D10: =B10-C10 -> 15408488 | E10: =B10-F10 -> 19519088 | F10: =0 -> 0 | G10: =IFERROR(B10/C10,0) -> 4.7484766 | H10: =IFERROR(E10/C10,0) -> 4.7484766 | I10: =IFERROR(SUM(AR_Aging!$G:$G)/SUM(Monthly_PnL!$B:$B)*365,0) -> 89.724934 | J10: =IFERROR(SUM(AP_Aging!$G:$G)/SUM(Monthly_PnL!$E:$E)*365,0) -> 81.937677
A11: =DATE(2025,9,1) -> 45901 | B11: =SUM(AR_Aging!$G:$G)+INDEX(CashFlow!$L:$L,MATCH(A11,CashFlow!$A:$A,0)) -> 20615609 | C11: =SUM(AP_Aging!$G:$G) -> 4110600 | D11: =B11-C11 -> 16505009 | E11: =B11-F11 -> 20615609 | F11: =0 -> 0 | G11: =IFERROR(B11/C11,0) -> 5.0152311 | H11: =IFERROR(E11/C11,0) -> 5.0152311 | I11: =IFERROR(SUM(AR_Aging!$G:$G)/SUM(Monthly_PnL!$B:$B)*365,0) -> 89.724934 | J11: =IFERROR(SUM(AP_Aging!$G:$G)/SUM(Monthly_PnL!$E:$E)*365,0) -> 81.937677
A12: =DATE(2025,10,1) -> 45931 | B12: =SUM(AR_Aging!$G:$G)+INDEX(CashFlow!$L:$L,MATCH(A12,CashFlow!$A:$A,0)) -> 21582996 | C12: =SUM(AP_Aging!$G:$G) -> 4110600 | D12: =B12-C12 -> 17472396 | E12: =B12-F12 -> 21582996 | F12: =0 -> 0 | G12: =IFERROR(B12/C12,0) -> 5.2505707 | H12: =IFERROR(E12/C12,0) -> 5.2505707 | I12: =IFERROR(SUM(AR_Aging!$G:$G)/SUM(Monthly_PnL!$B:$B)*365,0) -> 89.724934 | J12: =IFERROR(SUM(AP_Aging!$G:$G)/SUM(Monthly_PnL!$E:$E)*365,0) -> 81.937677
A13: =DATE(2025,11,1) -> 45962 | B13: =SUM(AR_Aging!$G:$G)+INDEX(CashFlow!$L:$L,MATCH(A13,CashFlow!$A:$A,0)) -> 22847762 | C13: =SUM(AP_Aging!$G:$G) -> 4110600 | D13: =B13-C13 -> 18737162 | E13: =B13-F13 -> 22847762 | F13: =0 -> 0 | G13: =IFERROR(B13/C13,0) -> 5.5582547 | H13: =IFERROR(E13/C13,0) -> 5.5582547 | I13: =IFERROR(SUM(AR_Aging!$G:$G)/SUM(Monthly_PnL!$B:$B)*365,0) -> 89.724934 | J13: =IFERROR(SUM(AP_Aging!$G:$G)/SUM(Monthly_PnL!$E:$E)*365,0) -> 81.937677
A14: =DATE(2025,12,1) -> 45992 | B14: =SUM(AR_Aging!$G:$G)+INDEX(CashFlow!$L:$L,MATCH(A14,CashFlow!$A:$A,0)) -> 24245361 | C14: =SUM(AP_Aging!$G:$G) -> 4110600 | D14: =B14-C14 -> 20134761 | E14: =B14-F14 -> 24245361 | F14: =0 -> 0 | G14: =IFERROR(B14/C14,0) -> 5.8982535 | H14: =IFERROR(E14/C14,0) -> 5.8982535 | I14: =IFERROR(SUM(AR_Aging!$G:$G)/SUM(Monthly_PnL!$B:$B)*365,0) -> 89.724934 | J14: =IFERROR(SUM(AP_Aging!$G:$G)/SUM(Monthly_PnL!$E:$E)*365,0) -> 81.937677

Sheet Profitability
A1: Business_Unit | B1: Revenue | C1: Cost_of_Revenue | D1: Gross_Profit | E1: Allocated_Operating_Expense | F1: EBITDA | G1: EBITDA_Margin
A2: Software Development | B2: 12383900 | C2: 4334365 | D2: 8049535 | E2: 7407935.5 | F2: 641599.52 | G2: 0.051809165
A3: Website Development | B3: 7227700 | C3: 2529695 | D3: 4698005 | E3: 4323543.9 | F3: 374461.1 | G3: 0.051809165
A4: AMC & Maintenance | B4: 6036800 | C4: 2112880 | D4: 3923920 | E4: 3611158.4 | F4: 312761.57 | G4: 0.051809165
A5: IT Consulting | B5: 4962400 | C5: 1736840 | D5: 3225560 | E5: 2968462.2 | F5: 257097.8 | G5: 0.051809165

Sheet Forecast
A1: Month | B1: Metric | C1: Forecast
A2: 46023 | B2: Revenue | C2: 3133004.5
A3: 46054 | B3: Revenue | C3: 3222559.1
A4: 46082 | B4: Revenue | C4: 3312113.6
A5: 46113 | B5: Revenue | C5: 3401668.2
A6: 46143 | B6: Revenue | C6: 3491222.7
A7: 46174 | B7: Revenue | C7: 3580777.3
A8: 46204 | B8: Revenue | C8: 3670331.8
A9: 46235 | B9: Revenue | C9: 3759886.4
A10: 46266 | B10: Revenue | C10: 3849440.9
A11: 46296 | B11: Revenue | C11: 3938995.5
A12: 46327 | B12: Revenue | C12: 4028550
A13: 46357 | B13: Revenue | C13: 4118104.5
... A37: 46357 | B37: Net_Profit | C37: 435191.48

Sheet Scenarios
A1: Scenario | B1: Revenue_Factor | C1: Expense_Factor | D1: Revenue | E1: Expenses | F1: Gross_Profit | G1: EBITDA | H1: Net_Profit
A2: Base | B2: 1 | C2: 1 | D2: 3154500 | E2: 1735800 | F2: 2050425 | G2: 314625 | H2: 235968.75
A3: Upside | B3: 1.1 | C3: 0.97 | D3: 3469950 | E3: 1683726 | F3: 2255467.5 | G3: 571741.5 | H3: 428806.13
A4: Downside | B4: 0.9 | C4: 1.08 | D4: 2839050 | E4: 1874664 | F4: 1845382.5 | G4: -29281.5 | H4: -29281.5

Sheet Risk_Alerts
A1: Alert_Type | B1: Severity | C1: Entity | D1: Message
A2: Budget Utilization | B2: HIGH | C2: Engineering | D2: Utilization 92.5% exceeds 90% threshold
A3: Budget Utilization | B3: HIGH | C3: Finance & Admin | D3: Utilization 94.3% exceeds 90% threshold
A4: Budget Utilization | B4: HIGH | C4: IT | D4: Utilization 90.8% exceeds 90% threshold
A5: Budget Utilization | B5: HIGH | C5: Operations | D5: Utilization 93.4% exceeds 90% threshold
A6: Budget Utilization | B6: HIGH | C6: Sales & Marketing | D6: Utilization 95.2% exceeds 90% threshold
A7: Credit Risk | B7: HIGH | C7: Bright Retail | D7: Invoice AR-5002 overdue 334 days
A8: Credit Risk | B8: HIGH | C8: Crest Healthcare | D8: Invoice AR-5003 overdue 334 days
A9: Credit Risk | B9: HIGH | C9: Delta Logistics | D9: Invoice AR-5004 overdue 334 days
A10: Credit Risk | B10: HIGH | C10: Evergreen Finance | D10: Invoice AR-5005 overdue 334 days
A11: Credit Risk | B11: HIGH | C11: Bright Retail | D11: Invoice AR-5006 overdue 303 days
A12: Credit Risk | B12: HIGH | C12: Crest Healthcare | D12: Invoice AR-5007 overdue 303 days
... A42: Credit Risk | B42: HIGH | C42: Alpha Industries | D42: Invoice AR-5045 overdue 91 days

Sheet Data_Quality
A1: Check | B1: Issue_Count | C1: Status
A2: Revenue missing values | B2: 0 | C2: PASS
A3: Expense missing values | B3: 0 | C3: PASS
A4: AR negative outstanding | B4: 0 | C4: PASS
A5: AP negative outstanding | B5: 0 | C5: PASS
A6: Cash-flow reconciliation | B6: 0 | C6: PASS

Sheet Database_Design
A1: Table | B1: Primary Key | C1: Important Fields | D1: Purpose
A2: Revenue | B2: Invoice_ID | C2: Date, Business_Unit, Region, Customer, Revenue, Currency | D2: Revenue transaction fact
A3: Expenses | B3: Expense_ID | C3: Date, Department, Category, Actual_Expense | D3: Expense transaction fact
A4: Budget | B4: Department | C4: Annual_Budget, Annual_Actual, Variance, Utilization_% | D4: Annual department budget
A5: Monthly_Budget | B5: Month+Department | C5: Budget | D5: Monthly budget allocation
A6: AR_Aging | B6: Invoice_Number | C6: Customer, Invoice_Date, Due_Date, Amounts, Days_Overdue, Aging_Bucket | D6: Receivables aging
A7: AP_Aging | B7: Bill_Number | C7: Vendor, Bill_Date, Due_Date, Amounts, Days_Overdue, Aging_Bucket | D7: Payables aging
A8: CashFlow | B8: Month | C8: Opening_Cash, Inflows, Outflows, Closing_Cash | D8: Cash-flow statement
A9: Working_Capital | B9: Month | C9: Cash, AR, Inventory, Current_Assets, Current_Liabilities | D9: Liquidity KPIs
A10: Forecast | B10: Month+Metric | C10: Forecast | D10: Forward-looking estimates
A11: Risk_Alerts | B11: Alert_Type+Entity | C11: Severity, Message | D11: Rule-based risk detection

Sheet Formula_Guide
A1: Metric | B1: Formula / Logic
A2: Budget Variance | B2: Actual - Budget
A3: Budget Utilization % | B3: Actual / Budget
A4: Closing Cash | B4: Opening Cash + Total Inflows - Total Outflows
A5: Outstanding AR | B5: Invoice Amount - Paid Amount
A6: Days Overdue | B6: MAX(As-of Date - Due Date, 0) for unpaid balances
A7: Gross Profit | B7: Revenue - Cost of Revenue
A8: Gross Margin | B8: Gross Profit / Revenue
A9: EBITDA | B9: Gross Profit - Operating Expenses
A10: EBITDA Margin | B10: EBITDA / Revenue
A11: EBIT | B11: EBITDA - D&A
A12: Net Profit | B12: EBIT - Tax
... A21: Expense Growth Alert | B21: Month-on-month expense growth > 20%

Sheet Monthly_PnL
A1: MONTHLY P&L | FORMULA-DRIVEN
A2: Month | B2: Revenue | C2: Cost of Revenue | D2: Gross Profit | E2: Operating Expenses | F2: EBITDA | G2: D&A | H2: EBIT | I2: Tax | J2: Net Profit | K2: Gross Margin | L2: Net Margin
A3: =DATE(2025,1,1) -> 45658 | B3: =SUMIFS(Revenue!$F:$F,Revenue!$B:$B,">="&A3,Revenue!$B:$B,"<"&EDATE(A3,1)) -> 2059800 | C3: =B3*35% -> 720930 | D3: =B3-C3 -> 1338870 | E3: =SUMIFS(Expenses!$E:$E,Expenses!$B:$B,">="&A3,Expenses!$B:$B,"<"&EDATE(A3,1)) -> 1366200 | F3: =D3-E3 -> -27330 | G3: =B3*2.5% -> 51495 | H3: =F3-G3 -> -78825 | I3: =MAX(H3*25%,0) -> 0 | J3: =H3-I3 -> -78825 | K3: =IFERROR(D3/B3,0) -> 0.65 | L3: =IFERROR(J3/B3,0) -> -0.038268278
A4: =DATE(2025,2,1) -> 45689 | B4: =SUMIFS(Revenue!$F:$F,Revenue!$B:$B,">="&A4,Revenue!$B:$B,"<"&EDATE(A4,1)) -> 2160300 | C4: =B4*35% -> 756105 | D4: =B4-C4 -> 1404195 | E4: =SUMIFS(Expenses!$E:$E,Expenses!$B:$B,">="&A4,Expenses!$B:$B,"<"&EDATE(A4,1)) -> 1424700 | F4: =D4-E4 -> -20505 | G4: =B4*2.5% -> 54007.5 | H4: =F4-G4 -> -74512.5 | I4: =MAX(H4*25%,0) -> 0 | J4: =H4-I4 -> -74512.5 | K4: =IFERROR(D4/B4,0) -> 0.65 | L4: =IFERROR(J4/B4,0) -> -0.034491737
A5: =DATE(2025,3,1) -> 45717 | B5: =SUMIFS(Revenue!$F:$F,Revenue!$B:$B,">="&A5,Revenue!$B:$B,"<"&EDATE(A5,1)) -> 2263000 | C5: =B5*35% -> 792050 | D5: =B5-C5 -> 1470950 | E5: =SUMIFS(Expenses!$E:$E,Expenses!$B:$B,">="&A5,Expenses!$B:$B,"<"&EDATE(A5,1)) -> 1427600 | F5: =D5-E5 -> 43350 | G5: =B5*2.5% -> 56575 | H5: =F5-G5 -> -13225 | I5: =MAX(H5*25%,0) -> 0 | J5: =H5-I5 -> -13225 | K5: =IFERROR(D5/B5,0) -> 0.65 | L5: =IFERROR(J5/B5,0) -> -0.0058440124
A6: =DATE(2025,4,1) -> 45748 | B6: =SUMIFS(Revenue!$F:$F,Revenue!$B:$B,">="&A6,Revenue!$B:$B,"<"&EDATE(A6,1)) -> 2344800 | C6: =B6*35% -> 820680 | D6: =B6-C6 -> 1524120 | E6: =SUMIFS(Expenses!$E:$E,Expenses!$B:$B,">="&A6,Expenses!$B:$B,"<"&EDATE(A6,1)) -> 1487600 | F6: =D6-E6 -> 36520 | G6: =B6*2.5% -> 58620 | H6: =F6-G6 -> -22100 | I6: =MAX(H6*25%,0) -> 0 | J6: =H6-I6 -> -22100 | K6: =IFERROR(D6/B6,0) -> 0.65 | L6: =IFERROR(J6/B6,0) -> -0.0094251109
A7: =DATE(2025,5,1) -> 45778 | B7: =SUMIFS(Revenue!$F:$F,Revenue!$B:$B,">="&A7,Revenue!$B:$B,"<"&EDATE(A7,1)) -> 2428100 | C7: =B7*35% -> 849835 | D7: =B7-C7 -> 1578265 | E7: =SUMIFS(Expenses!$E:$E,Expenses!$B:$B,">="&A7,Expenses!$B:$B,"<"&EDATE(A7,1)) -> 1446400 | F7: =D7-E7 -> 131865 | G7: =B7*2.5% -> 60702.5 | H7: =F7-G7 -> 71162.5 | I7: =MAX(H7*25%,0) -> 17790.625 | J7: =H7-I7 -> 53371.875 | K7: =IFERROR(D7/B7,0) -> 0.65 | L7: =IFERROR(J7/B7,0) -> 0.021980921
A8: =DATE(2025,6,1) -> 45809 | B8: =SUMIFS(Revenue!$F:$F,Revenue!$B:$B,">="&A8,Revenue!$B:$B,"<"&EDATE(A8,1)) -> 2536500 | C8: =B8*35% -> 887775 | D8: =B8-C8 -> 1648725 | E8: =SUMIFS(Expenses!$E:$E,Expenses!$B:$B,">="&A8,Expenses!$B:$B,"<"&EDATE(A8,1)) -> 1507200 | F8: =D8-E8 -> 141525 | G8: =B8*2.5% -> 63412.5 | H8: =F8-G8 -> 78112.5 | I8: =MAX(H8*25%,0) -> 19528.125 | J8: =H8-I8 -> 58584.375 | K8: =IFERROR(D8/B8,0) -> 0.65 | L8: =IFERROR(J8/B8,0) -> 0.023096541
A9: =DATE(2025,7,1) -> 45839 | B9: =SUMIFS(Revenue!$F:$F,Revenue!$B:$B,">="&A9,Revenue!$B:$B,"<"&EDATE(A9,1)) -> 2526700 | C9: =B9*35% -> 884345 | D9: =B9-C9 -> 1642355 | E9: =SUMIFS(Expenses!$E:$E,Expenses!$B:$B,">="&A9,Expenses!$B:$B,"<"&EDATE(A9,1)) -> 1554200 | F9: =D9-E9 -> 88155 | G9: =B9*2.5% -> 63167.5 | H9: =F9-G9 -> 24987.5 | I9: =MAX(H9*25%,0) -> 6246.875 | J9: =H9-I9 -> 18740.625 | K9: =IFERROR(D9/B9,0) -> 0.65 | L9: =IFERROR(J9/B9,0) -> 0.0074170361
A10: =DATE(2025,8,1) -> 45870 | B10: =SUMIFS(Revenue!$F:$F,Revenue!$B:$B,">="&A10,Revenue!$B:$B,"<"&EDATE(A10,1)) -> 2637700 | C10: =B10*35% -> 923195 | D10: =B10-C10 -> 1714505 | E10: =SUMIFS(Expenses!$E:$E,Expenses!$B:$B,">="&A10,Expenses!$B:$B,"<"&EDATE(A10,1)) -> 1511300 | F10: =D10-E10 -> 203205 | G10: =B10*2.5% -> 65942.5 | H10: =F10-G10 -> 137262.5 | I10: =MAX(H10*25%,0) -> 34315.625 | J10: =H10-I10 -> 102946.88 | K10: =IFERROR(D10/B10,0) -> 0.65 | L10: =IFERROR(J10/B10,0) -> 0.039029031
A11: =DATE(2025,9,1) -> 45901 | B11: =SUMIFS(Revenue!$F:$F,Revenue!$B:$B,">="&A11,Revenue!$B:$B,"<"&EDATE(A11,1)) -> 2725900 | C11: =B11*35% -> 954065 | D11: =B11-C11 -> 1771835 | E11: =SUMIFS(Expenses!$E:$E,Expenses!$B:$B,">="&A11,Expenses!$B:$B,"<"&EDATE(A11,1)) -> 1604100 | F11: =D11-E11 -> 167735 | G11: =B11*2.5% -> 68147.5 | H11: =F11-G11 -> 99587.5 | I11: =MAX(H11*25%,0) -> 24896.875 | J11: =H11-I11 -> 74690.625 | K11: =IFERROR(D11/B11,0) -> 0.65 | L11: =IFERROR(J11/B11,0) -> 0.027400354
A12: =DATE(2025,10,1) -> 45931 | B12: =SUMIFS(Revenue!$F:$F,Revenue!$B:$B,">="&A12,Revenue!$B:$B,"<"&EDATE(A12,1)) -> 2815700 | C12: =B12*35% -> 985495 | D12: =B12-C12 -> 1830205 | E12: =SUMIFS(Expenses!$E:$E,Expenses!$B:$B,">="&A12,Expenses!$B:$B,"<"&EDATE(A12,1)) -> 1575600 | F12: =D12-E12 -> 254605 | G12: =B12*2.5% -> 70392.5 | H12: =F12-G12 -> 184212.5 | I12: =MAX(H12*25%,0) -> 46053.125 | J12: =H12-I12 -> 138159.38 | K12: =IFERROR(D12/B12,0) -> 0.65 | L12: =IFERROR(J12/B12,0) -> 0.049067505
A13: =DATE(2025,11,1) -> 45962 | B13: =SUMIFS(Revenue!$F:$F,Revenue!$B:$B,">="&A13,Revenue!$B:$B,"<"&EDATE(A13,1)) -> 2957800 | C13: =B13*35% -> 1035230 | D13: =B13-C13 -> 1922570 | E13: =SUMIFS(Expenses!$E:$E,Expenses!$B:$B,">="&A13,Expenses!$B:$B,"<"&EDATE(A13,1)) -> 1670400 | F13: =D13-E13 -> 252170 | G13: =B13*2.5% -> 73945 | H13: =F13-G13 -> 178225 | I13: =MAX(H13*25%,0) -> 44556.25 | J13: =H13-I13 -> 133668.75 | K13: =IFERROR(D13/B13,0) -> 0.65 | L13: =IFERROR(J13/B13,0) -> 0.04519195
A14: =DATE(2025,12,1) -> 45992 | B14: =SUMIFS(Revenue!$F:$F,Revenue!$B:$B,">="&A14,Revenue!$B:$B,"<"&EDATE(A14,1)) -> 3154500 | C14: =B14*35% -> 1104075 | D14: =B14-C14 -> 2050425 | E14: =SUMIFS(Expenses!$E:$E,Expenses!$B:$B,">="&A14,Expenses!$B:$B,"<"&EDATE(A14,1)) -> 1735800 | F14: =D14-E14 -> 314625 | G14: =B14*2.5% -> 78862.5 | H14: =F14-G14 -> 235762.5 | I14: =MAX(H14*25%,0) -> 58940.625 | J14: =H14-I14 -> 176821.88 | K14: =IFERROR(D14/B14,0) -> 0.65 | L14: =IFERROR(J14/B14,0) -> 0.056053852

Sheet HELPER TABLE
B2: 1. MONTHLY REVENUE | E2: 2. REVENUE VS OPERATING EXPENSES | I2: 3. PROFIT TREND | N2: 4. EXPENSE DISTRIBUTION | Q2: 5. BUDGET VS ACTUAL
B3: Month | C3: Revenue | E3: Month | F3: Revenue | G3: Expenses | I3: Month | J3: Revenue | K3: EBITDA | L3: Net Profit | N3: Category | O3: Amount | Q3: Department | R3: Budget | S3: Actual
B4: 45658 | C4: =Monthly_PnL!B3 -> 2059800 | E4: 45658 | F4: =Monthly_PnL!B3 -> 2059800 | G4: =Monthly_PnL!E3 -> 1366200 | I4: 45658 | J4: 2059800 | K4: =Monthly_PnL!H3 -> -78825 | L4: -78825 | N4: Employee Costs | O4: 9457400 | Q4: Engineering | R4: 10809700 | S4: 10009000
B5: 45689 | C5: =Monthly_PnL!B4 -> 2160300 | E5: 45689 | F5: =Monthly_PnL!B4 -> 2160300 | G5: =Monthly_PnL!E4 -> 1424700 | I5: 45689 | J5: 2160300 | K5: -20505 | L5: -74513 | N5: Infrastructure | O5: 2167500 | Q5: IT | R5: 3135800 | S5: 2850700
B6: 45717 | C6: =Monthly_PnL!B5 -> 2263000 | E6: 45717 | F6: =Monthly_PnL!B5 -> 2263000 | G6: =Monthly_PnL!E5 -> 1427600 | I6: 45717 | J6: 2263000 | K6: 43350 | L6: -13225 | N6: Marketing | O6: 1839100 | Q6: Sales & Marketing | R6: 1931100 | S6: 1839100
B7: 45748 | C7: =Monthly_PnL!B6 -> 2344800 | E7: 45748 | F7: =Monthly_PnL!B6 -> 2344800 | G7: =Monthly_PnL!E6 -> 1487600 | I7: 45748 | J7: 2344800 | K7: 36520 | L7: -22100 | N7: Travel | O7: 853900 | Q7: Operations | R7: 913700 | S7: 853900
B8: 45778 | C8: =Monthly_PnL!B7 -> 2428100 | E8: 45778 | F8: =Monthly_PnL!B7 -> 2428100 | G8: =Monthly_PnL!E7 -> 1446400 | I8: 45778 | J8: 2428100 | K8: 131865 | L8: 53372 | N8: Software | O8: 1510500 | Q8: HR | R8: 1691800 | S8: 1510500
B9: 45809 | C9: =Monthly_PnL!B8 -> 2536500 | E9: 45809 | F9: =Monthly_PnL!B8 -> 2536500 | G9: =Monthly_PnL!E8 -> 1507200 | I9: 45809 | J9: 2536500 | K9: 141525 | L9: 58584 | N9: Professional Fees | O9: 0 | Q9: Finance & Admin | R9: 1322800 | S9: 1247900
B10: 45839 | C10: =Monthly_PnL!B9 -> 2526700 | E10: 45839 | F10: =Monthly_PnL!B9 -> 2526700 | G10: =Monthly_PnL!E9 -> 1554200 | I10: 45839 | J10: 2526700 | K10: 88155 | L10: 18741 | N10: Office Expenses | O10: 0
B11: 45870 | C11: =Monthly_PnL!B10 -> 2637700 | E11: 45870 | F11: =Monthly_PnL!B10 -> 2637700 | G11: =Monthly_PnL!E10 -> 1511300 | I11: 45870 | J11: 2637700 | K11: 203205 | L11: 102947 | N11: Other | O11: 0
B12: 45901 | C12: =Monthly_PnL!B11 -> 2725900 | E12: 45901 | F12: =Monthly_PnL!B11 -> 2725900 | G12: =Monthly_PnL!E11 -> 1604100 | I12: 45901 | J12: 2725900 | K12: 167735 | L12: 74691
B13: 45931 | C13: =Monthly_PnL!B12 -> 2815700 | E13: 45931 | F13: =Monthly_PnL!B12 -> 2815700 | G13: =Monthly_PnL!E12 -> 1575600 | I13: 45931 | J13: 2815700 | K13: 254605 | L13: 138159
B14: 45962 | C14: =Monthly_PnL!B13 -> 2957800 | E14: 45962 | F14: =Monthly_PnL!B13 -> 2957800 | G14: =Monthly_PnL!E13 -> 1670400 | I14: 45962 | J14: 2957800 | K14: Formula-driven helper tables | L14: 133669
B15: 45992 | C15: =Monthly_PnL!B14 -> 3154500 | E15: 45992 | F15: =Monthly_PnL!B14 -> 3154500 | G15: =Monthly_PnL!E14 -> 1735800 | I15: 45992 | J15: 3154500 | K15: Do not manually overwrite calculated cells. | L15: 176822
B20: 6. CLOSING CASH TREND | E20: 7. AR AGING | I20: 8. AP AGING
B21: Month | C21: Closing Cash | E21: Aging Bucket | F21: Outstanding | I21: Aging Bucket | J21: Outstanding
B22: 45658 | C22: =CashFlow!L2 -> 5645507 | E22: 0-30 | F22: 1562300 | I22: 0-30 | J22: 781100
B23: 45689 | C23: =CashFlow!L3 -> 6337876 | E23: 31-60 | F23: 0 | I23: 31-60 | J23: 0
B24: 45717 | C24: =CashFlow!L4 -> 7282950 | E24: 61-90 | F24: 690500 | I24: 61-90 | J24: 388900
B25: 45748 | C25: =CashFlow!L5 -> 8103950 | E25: 90+ | F25: 5272000 | I25: 90+ | J25: 2940600
B26: 45778 | C26: =CashFlow!L6 -> 8801829
B27: 45809 | C27: =CashFlow!L7 -> 9798552
B28: 45839 | C28: =CashFlow!L8 -> 10747637
B29: 45870 | C29: =CashFlow!L9 -> 11994288
B30: 45901 | C30: =CashFlow!L10 -> 13090809
B31: 45931 | C31: =CashFlow!L11 -> 14058196
B32: 45962 | C32: =CashFlow!L12 -> 15322962
B33: 45992 | C33: =CashFlow!L13 -> 16720561
